{
  "$schema": "https://ui.shadcn.com/schema/registry-item.json",
  "name": "field-input",
  "registryDependencies": [
    "field"
  ],
  "files": [
    {
      "path": "registry/new-york-v4/examples/field-input.tsx",
      "content": "import {\n  Field,\n  FieldDescription,\n  FieldGroup,\n  FieldLabel,\n  FieldSet,\n} from \"@/registry/new-york-v4/ui/field\"\nimport { Input } from \"@/registry/new-york-v4/ui/input\"\n\nexport default function FieldInput() {\n  return (\n    <div className=\"w-full max-w-md\">\n      <FieldSet>\n        <FieldGroup>\n          <Field>\n            <FieldLabel htmlFor=\"username\">ユーザー名</FieldLabel>\n            <Input id=\"username\" type=\"text\" placeholder=\"山田太郎\" />\n            <FieldDescription>\n              アカウントのユニークなユーザー名を選んでください。\n            </FieldDescription>\n          </Field>\n          <Field>\n            <FieldLabel htmlFor=\"password\">パスワード</FieldLabel>\n            <FieldDescription>\n              8文字以上で入力してください。\n            </FieldDescription>\n            <Input id=\"password\" type=\"password\" placeholder=\"••••••••\" />\n          </Field>\n        </FieldGroup>\n      </FieldSet>\n    </div>\n  )\n}\n",
      "type": "registry:example"
    }
  ],
  "type": "registry:example"
}